empirical_distribution/__init__.py
empirical_distribution/version.py
empirical_distribution/tests/__init__.py
empirical_distribution/tests/tests.py
empirical_distribution-0.0.1.dist-info/METADATA
empirical_distribution-0.0.1.dist-info/RECORD
empirical_distribution-0.0.1.dist-info/WHEEL
empirical_distribution-0.0.1.dist-info/top_level.txt
