Metadata-Version: 2.1
Name: empirical-distribution
Version: 0.0.1
Summary: UNKNOWN
Home-page: https://github.com/robdmc/empirical-distribution
Author: Rob deCarvalho
Author-email: unlisted@unlisted.net
License: MIT
Platform: UNKNOWN
Classifier: Programming Language :: Python :: 2.7
Classifier: Programming Language :: Python :: 3.4
Classifier: Programming Language :: Python :: 3.5
Classifier: Intended Audience :: Developers
Classifier: License :: OSI Approved :: MIT License
Classifier: Operating System :: OS Independent
Provides-Extra: dev
Provides-Extra: dev
Requires-Dist: coverage; extra == 'dev'
Requires-Dist: flake8; extra == 'dev'
Requires-Dist: mock; extra == 'dev'
Requires-Dist: nose; extra == 'dev'
Requires-Dist: wheel; extra == 'dev'
Requires-Dist: Sphinx; extra == 'dev'
Requires-Dist: sphinx-rtd-theme; extra == 'dev'
